zhige_tools/__init__.py
zhige_tools/base_converter.py
zhige_tools-0.1.2.dist-info/LICENSE
zhige_tools-0.1.2.dist-info/METADATA
zhige_tools-0.1.2.dist-info/WHEEL
zhige_tools-0.1.2.dist-info/top_level.txt
zhige_tools-0.1.2.dist-info/RECORD
